{
  "games": 40,
  "seed": 20260607,
  "caps": [
    1,
    2,
    4,
    8,
    12
  ],
  "opponents": [
    "hoarder",
    "word-ev-max"
  ],
  "results": {
    "base": {
      "games": 40,
      "top1": 0.35,
      "top2_survive": 0.7,
      "last": 0.3,
      "avg_rank": 1.95,
      "avg_score": 145.225,
      "avg_score_delta": -21.8,
      "avg_balance": 7.15
    },
    "uncapped": {
      "games": 40,
      "top1": 0.2,
      "top2_survive": 0.5,
      "last": 0.5,
      "avg_rank": 2.3,
      "avg_score": 127.425,
      "avg_score_delta": -51.025,
      "avg_balance": 9.4
    },
    "cap-1": {
      "games": 40,
      "top1": 0.225,
      "top2_survive": 0.525,
      "last": 0.475,
      "avg_rank": 2.25,
      "avg_score": 131.075,
      "avg_score_delta": -47.075,
      "avg_balance": 7.975
    },
    "cap-2": {
      "games": 40,
      "top1": 0.25,
      "top2_survive": 0.525,
      "last": 0.475,
      "avg_rank": 2.225,
      "avg_score": 129.2,
      "avg_score_delta": -36.4,
      "avg_balance": 9.775
    },
    "cap-4": {
      "games": 40,
      "top1": 0.2,
      "top2_survive": 0.525,
      "last": 0.475,
      "avg_rank": 2.275,
      "avg_score": 127.275,
      "avg_score_delta": -49.175,
      "avg_balance": 9.425
    },
    "cap-8": {
      "games": 40,
      "top1": 0.25,
      "top2_survive": 0.625,
      "last": 0.375,
      "avg_rank": 2.125,
      "avg_score": 141.4,
      "avg_score_delta": -25.675,
      "avg_balance": 9.325
    },
    "cap-12": {
      "games": 40,
      "top1": 0.325,
      "top2_survive": 0.575,
      "last": 0.425,
      "avg_rank": 2.1,
      "avg_score": 139.05,
      "avg_score_delta": -21.2,
      "avg_balance": 9.625
    }
  }
}